test.py
DataExpansion/__init__.py
DataExpansion/sqlite_class.py
DataExpansion-0.1.6.dist-info/LICENSE
DataExpansion-0.1.6.dist-info/METADATA
DataExpansion-0.1.6.dist-info/WHEEL
DataExpansion-0.1.6.dist-info/top_level.txt
DataExpansion-0.1.6.dist-info/RECORD
